newdoc/__init__.py
newdoc/newdoc.py
newdoc/templates/assembly_title.adoc
newdoc/templates/con_title.adoc
newdoc/templates/proc_title.adoc
newdoc/templates/ref_title.adoc
newdoc-1.5.1.dist-info/LICENSE
newdoc-1.5.1.dist-info/METADATA
newdoc-1.5.1.dist-info/WHEEL
newdoc-1.5.1.dist-info/entry_points.txt
newdoc-1.5.1.dist-info/top_level.txt
newdoc-1.5.1.dist-info/RECORD
